{
    "id": "0097887-39.2018.8.05.0001",
    "judge": "LIVIA DE MELO BARBOSA ",
    "court": "1ª VSJE DO CONSUMIDOR (MATUTINO) ",
    "date": "23 de Julho de 2018",
    "class": "Procedimento do Juizado Especial Cível « Procedimento de Conhecimento « Processo de Conhecimento « PROCESSO CÍVEL E DO TRABALHO",
    "subject": "Inclusão Indevida em Cadastro de Inadimplentes « Indenização por Dano Moral « Responsabilidade do Fornecedor « DIREITO DO CONSUMIDOR  ",
    "phase": "CONHECIMENTO ",
    "situation": "  ",
    "value": "R$ 18.000,00",
    "lastest event": "Citação expedido(a)",
    "active party": [
        "EDMAR NASCIMENTO SANTOS    ",
        ""
    ],
    "lawyer active": "FELIPE AUGUSTO SANTIAGO GUIMARAES   38049N-BA",
    "passive party": [
        "EMBRATEL TVSAT TELECOMUNICACOES S A       ",
        ""
    ],
    "lawyer passive": " Nenhum advogado cadastrado.",
    "follow up": {
        "0": [
            "23/07/18",
            "Citação expedido(a)",
            "  Para EMBRATEL TVSAT TELECOMUNICACOES S A"
        ],
        "1": [
            "23/07/18",
            "Intimação lido(a)",
            "  (Para EDMAR NASCIMENTO SANTOS) em 23/07/18 *Referente ao evento Audiência  Una Designada(23/07/18)"
        ],
        "2": [
            "23/07/18",
            "Audiência  Una Designada",
            "  (Agendada para 24 de Agosto de 2018 às 09:40 h)"
        ],
        "3": [
            "23/07/18",
            "Distribuído por Sorteio",
            "  1ª VSJE DO CONSUMIDOR (MATUTINO)"
        ],
        "4": [
            "23/07/18",
            "Recebido pelo Distribuidor",
            "  Origem: OAB38049NBA"
        ]
    }
}